pyecobee/__init__.py
pyecobee/ecobee_object.py
pyecobee/enumerations.py
pyecobee/exceptions.py
pyecobee/responses.py
pyecobee/service.py
pyecobee/utilities.py
pyecobee/objects/__init__.py
pyecobee/objects/action.py
pyecobee/objects/alert.py
pyecobee/objects/audio.py
pyecobee/objects/climate.py
pyecobee/objects/demand_management.py
pyecobee/objects/demand_response.py
pyecobee/objects/device.py
pyecobee/objects/ecobee_object.py
pyecobee/objects/electricity.py
pyecobee/objects/electricity_device.py
pyecobee/objects/electricity_tier.py
pyecobee/objects/energy.py
pyecobee/objects/equipment_setting.py
pyecobee/objects/event.py
pyecobee/objects/extended_runtime.py
pyecobee/objects/function.py
pyecobee/objects/general_setting.py
pyecobee/objects/group.py
pyecobee/objects/hierarchy_privilege.py
pyecobee/objects/hierarchy_set.py
pyecobee/objects/hierarchy_user.py
pyecobee/objects/house_details.py
pyecobee/objects/limit_setting.py
pyecobee/objects/location.py
pyecobee/objects/management.py
pyecobee/objects/meter_report.py
pyecobee/objects/meter_report_data.py
pyecobee/objects/notification_settings.py
pyecobee/objects/output.py
pyecobee/objects/page.py
pyecobee/objects/program.py
pyecobee/objects/remote_sensor.py
pyecobee/objects/remote_sensor_capability.py
pyecobee/objects/report_job.py
pyecobee/objects/runtime.py
pyecobee/objects/runtime_report.py
pyecobee/objects/runtime_sensor_metadata.py
pyecobee/objects/runtime_sensor_report.py
pyecobee/objects/security_settings.py
pyecobee/objects/selection.py
pyecobee/objects/sensor.py
pyecobee/objects/settings.py
pyecobee/objects/state.py
pyecobee/objects/status.py
pyecobee/objects/technician.py
pyecobee/objects/thermostat.py
pyecobee/objects/time_of_use.py
pyecobee/objects/user.py
pyecobee/objects/utility.py
pyecobee/objects/version.py
pyecobee/objects/voice_engine.py
pyecobee/objects/weather.py
pyecobee/objects/weather_forecast.py
pyecobee-1.3.11.dist-info/LICENSE
pyecobee-1.3.11.dist-info/METADATA
pyecobee-1.3.11.dist-info/WHEEL
pyecobee-1.3.11.dist-info/top_level.txt
pyecobee-1.3.11.dist-info/RECORD
