Metadata-Version: 2.1
Name: pyecobee
Version: 1.3.11
Summary: A Python implementation of the ecobee API
Home-page: https://github.com/sfanous/Pyecobee
Author: Sherif Fanous
Author-email: pyecobee_support@gmail.com
License: MIT
Platform: UNKNOWN
Classifier: Development Status :: 5 - Production/Stable
Classifier: Intended Audience :: Developers
Classifier: Natural Language :: English
Classifier: License :: OSI Approved :: MIT License
Classifier: Programming Language :: Python
Classifier: Programming Language :: Python :: 2.6
Classifier: Programming Language :: Python :: 2.7
Classifier: Programming Language :: Python :: 3
Classifier: Programming Language :: Python :: 3.3
Classifier: Programming Language :: Python :: 3.4
Classifier: Programming Language :: Python :: 3.5
Classifier: Programming Language :: Python :: 3.6
Classifier: Programming Language :: Python :: 3.7
Classifier: Programming Language :: Python :: 3.8
Classifier: Programming Language :: Python :: 3.9
Classifier: Programming Language :: Python :: Implementation :: CPython
Requires-Dist: pytz (>=2017.2)
Requires-Dist: requests (>=2.13.0)
Requires-Dist: six (>=1.10.0)
Requires-Dist: enum34 (>=1.1.6) ; python_version < "3.4"
